hippy_chat/__init__.py
hippy_chat/handler.py
hippy_chat/exec/__init__.py
hippy_chat/exec/demo.py
hippy_chat-0.3.0.dist-info/DESCRIPTION.rst
hippy_chat-0.3.0.dist-info/METADATA
hippy_chat-0.3.0.dist-info/RECORD
hippy_chat-0.3.0.dist-info/WHEEL
hippy_chat-0.3.0.dist-info/entry_points.txt
hippy_chat-0.3.0.dist-info/metadata.json
hippy_chat-0.3.0.dist-info/top_level.txt
tests/__init__.py
tests/test_handler.py
